aiverify_accumulated_local_effect/__init__.py
aiverify_accumulated_local_effect/__main__.py
aiverify_accumulated_local_effect/algo.meta.json
aiverify_accumulated_local_effect/algo.py
aiverify_accumulated_local_effect/algo_init.py
aiverify_accumulated_local_effect/input.schema.json
aiverify_accumulated_local_effect/output.schema.json
aiverify_accumulated_local_effect/plugin_init.py
aiverify_accumulated_local_effect-2.1.0.dist-info/METADATA
aiverify_accumulated_local_effect-2.1.0.dist-info/WHEEL
aiverify_accumulated_local_effect-2.1.0.dist-info/entry_points.txt
aiverify_accumulated_local_effect-2.1.0.dist-info/licenses/AUTHORS.rst
aiverify_accumulated_local_effect-2.1.0.dist-info/licenses/LICENSE
aiverify_accumulated_local_effect-2.1.0.dist-info/licenses/NOTICE.md
aiverify_accumulated_local_effect-2.1.0.dist-info/RECORD
