Metadata-Version: 2.4
Name: aiverify-accumulated-local-effect
Version: 2.1.0
Summary: AI Verify implementation of the Accumulated Local Effect algorithm. The algorithm provides black box explainations of how features and their corresponding values influence the prediction of a model.
Author: AI Verify
License-File: AUTHORS.rst
License-File: LICENSE
License-File: NOTICE.md
Requires-Python: <3.13,>=3.10
Requires-Dist: aiverify-test-engine>=2.1.0
Requires-Dist: numpy==1.26.4
Requires-Dist: pandas==2.2.2
